paper2d_root_motion_baker-0.1.2.dist-info/licenses/LICENSE
src/__init__.py
src/cli.py
src/config.yaml
src/config_manager.py
src/image_processor.py
src/json_exporter.py
src/marker_detector.py
src/motion_calculator.py
paper2d_root_motion_baker-0.1.2.dist-info/METADATA
paper2d_root_motion_baker-0.1.2.dist-info/WHEEL
paper2d_root_motion_baker-0.1.2.dist-info/entry_points.txt
paper2d_root_motion_baker-0.1.2.dist-info/top_level.txt
paper2d_root_motion_baker-0.1.2.dist-info/RECORD
