Metadata-Version: 2.4
Name: paper2d-root-motion-baker
Version: 0.1.2
Summary: A Python tool for baking root motion data from PNG sequence frames into JSON format
Home-page: https://github.com/ocarina/paper2d-root-motion-baker
Author: ocarina
Classifier: Programming Language :: Python :: 3
Classifier: Programming Language :: Python :: 3.7
Classifier: Programming Language :: Python :: 3.8
Classifier: Programming Language :: Python :: 3.9
Classifier: Programming Language :: Python :: 3.10
Classifier: License :: OSI Approved :: MIT License
Classifier: Operating System :: OS Independent
Requires-Python: >=3.7
License-File: LICENSE
Requires-Dist: Pillow>=10.0.0
Requires-Dist: numpy>=1.24.3
Requires-Dist: PyYAML>=6.0.1
Dynamic: author
Dynamic: classifier
Dynamic: description
Dynamic: description-content-type
Dynamic: home-page
Dynamic: license-file
Dynamic: requires-dist
Dynamic: requires-python
Dynamic: summary
